{
    "1": {
        "question": "Koji je glavni izazov u kvantnoj fotonici dijamanta pomenut u članku?",
        "options": {
            "A": "Nedostatak visokokvalitetnih tankih filmova dijamanta",
            "B": "Nemogućnost proizvodnje centara boje u dijamantu",
            "C": "Visoka cena dijamantskih materijala",
            "D": "Ograničena dostupnost dijamantskih supstrata",
            "E": "Teškoća u postizanju niskih vremena koherencije"
        }
    },
    "2": {
        "question": "Koja tehnika izrade se koristi za proizvodnju dijamantskih membrana sa pravougaonim poprečnim presekom?",
        "options": {
            "A": "Ugaono jetkanje",
            "B": "Kvazi-izotropno jetkanje",
            "C": "Hemijsko taloženje iz pare",
            "D": "Laserska ablacija",
            "E": "Epitaksija molekularnog snopa"
        }
    },
    "3": {
        "question": "Koja je glavna prednost korišćenja metoda inverznog dizajna u dijamantskoj fotonici?",
        "options": {
            "A": "Smanjeni troškovi materijala",
            "B": "Pojednostavljeni procesi izrade",
            "C": "Efikasan dizajn uređaja sa superiornim performansama",
            "D": "Povećana dostupnost dijamantskih supstrata",
            "E": "Poboljšana vremena koherencije centara boje"
        }
    },
    "4": {
        "question": "Koja je teorijska maksimalna efikasnost spajanja inverzno dizajniranih vertikalnih spojnica?",
        "options": {
            "A": "25%",
            "B": "50%",
            "C": "75%",
            "D": "100%",
            "E": "10%"
        }
    },
    "5": {
        "question": "Koja je primarna funkcija vertikalne spojnice u dijamantskom fotonskom krugu?",
        "options": {
            "A": "Generisanje kvantne upletenosti",
            "B": "Spajanje svetlosti između slobodnog prostora i talasovodnih modova",
            "C": "Pojačavanje optičkih signala",
            "D": "Filtriranje specifičnih talasnih dužina",
            "E": "Skladištenje kvantnih informacija"
        }
    },
    "6": {
        "question": "Koja je vršna efikasnost vertikalnih spojnica kada se koriste multimodni vlakna (MMF)?",
        "options": {
            "A": "21%",
            "B": "26.5%",
            "C": "30%",
            "D": "15%",
            "E": "10%"
        }
    },
    "7": {
        "question": "Koje je glavno ograničenje tradicionalnih fotonskih dizajna u obradi dijamanta?",
        "options": {
            "A": "Nemogućnost integracije sa drugim materijalima",
            "B": "Nedostatak skalabilnosti",
            "C": "Nemogućnost uzimanja u obzir ograničenja izrade",
            "D": "Visoka potrošnja energije",
            "E": "Ograničena širina pojasa"
        }
    },
    "8": {
        "question": "Koja je svrha talasovodnih razdelnika u dijamantskom fotonskom krugu?",
        "options": {
            "A": "Generisanje laserske svetlosti",
            "B": "Razdvajanje optičkih signala",
            "C": "Detekcija kvantnih stanja",
            "D": "Skladištenje optičkih podataka",
            "E": "Filtriranje šuma"
        }
    },
    "9": {
        "question": "Koja je glavna korist korišćenja inverznog dizajna za dijamantske fotonske krugove?",
        "options": {
            "A": "Smanjeno vreme izrade",
            "B": "Poboljšane performanse uređaja i integracija",
            "C": "Niži troškovi materijala",
            "D": "Pojednostavljen proces dizajna",
            "E": "Povećana veličina uređaja"
        }
    },
    "10": {
        "question": "Koji je glavni izazov sa trenutnim platformama tankog filma dijamanta na silikatnom supstratu?",
        "options": {
            "A": "Visoka cena",
            "B": "Ograničena optička transparentnost",
            "C": "Nekompatibilnost sa najsavremenijim kvantnim optičkim eksperimentima",
            "D": "Prekomerna težina",
            "E": "Loša toplotna provodljivost"
        }
    },
    "11": {
        "question": "Koja je glavna prednost korišćenja membrana od galijum fosfida (GaP) na dijamantu?",
        "options": {
            "A": "Niži troškovi",
            "B": "Veća toplotna stabilnost",
            "C": "Efikasni rešetkasti spojnici",
            "D": "Povećana mehanička čvrstoća",
            "E": "Poboljšana električna provodljivost"
        }
    },
    "12": {
        "question": "Koja je glavna svrha zareza u dizajnu talasovoda?",
        "options": {
            "A": "Povećanje efikasnosti rasipanja",
            "B": "Smanjenje veličine uređaja",
            "C": "Povećanje optičkog pojačanja",
            "D": "Poboljšanje upravljanja toplotom",
            "E": "Olakšavanje električnih veza"
        }
    },
    "13": {
        "question": "Koji je glavni razlog pada performansi nakon 200 iteracija optimizacije?",
        "options": {
            "A": "Degradacija materijala",
            "B": "Nametanje ograničenja izrade",
            "C": "Povećana računarska složenost",
            "D": "Pregrevanje uređaja",
            "E": "Interferencija signala"
        }
    },
    "14": {
        "question": "Koja je glavna karakteristika inverzno dizajnirane vertikalne spojnice koja osigurava kompaktnost?",
        "options": {
            "A": "Korišćenje naprednih materijala",
            "B": "Direktno spajanje sa talasovodom širine 400 nm bez sužavanja",
            "C": "Integracija sa elektronskim komponentama",
            "D": "Korišćenje veće površine",
            "E": "Ugradnja elemenata za hlađenje"
        }
    },
    "15": {
        "question": "Koja je glavna prednost inverzno dizajnirane vertikalne spojnice u odnosu na konvencionalne rešetkaste spojnice?",
        "options": {
            "A": "Niži troškovi",
            "B": "Veća toplotna stabilnost",
            "C": "Selektivno spajanje sa TEM00 modom",
            "D": "Povećana mehanička čvrstoća",
            "E": "Poboljšana električna provodljivost"
        }
    },
    "16": {
        "question": "Koja je glavna korist korišćenja superkontinuumskog izvora svetlosti u eksperimentima?",
        "options": {
            "A": "Smanjena potrošnja energije",
            "B": "Širokopojasne performanse",
            "C": "Niži troškovi",
            "D": "Pojednostavljena postavka",
            "E": "Povećana veličina uređaja"
        }
    },
    "17": {
        "question": "Koji je glavni razlog za neslaganje između PMF i MMF merenja?",
        "options": {
            "A": "Različite talasne dužine lasera",
            "B": "Varijabilni indeksi prelamanja",
            "C": "Efikasno spajanje iz talasovodnog moda u mod slobodnog prostora",
            "D": "Nedosledna izrada uređaja",
            "E": "Fluktuacije temperature"
        }
    },
    "18": {
        "question": "Koji je glavni izazov u skaliranju kvantnih mreža pomenut u članku?",
        "options": {
            "A": "Visoka potrošnja energije",
            "B": "Ograničena širina pojasa",
            "C": "Efikasno prikupljanje i detekcija fotona",
            "D": "Povećana veličina uređaja",
            "E": "Složeni procesi izrade"
        }
    },
    "19": {
        "question": "Koja je glavna prednost korišćenja zadnjih reflektora u dizajnu?",
        "options": {
            "A": "Smanjeni troškovi materijala",
            "B": "Poboljšano upravljanje toplotom",
            "C": "Povećana efikasnost spajanja",
            "D": "Pojednostavljen proces izrade",
            "E": "Poboljšana mehanička stabilnost"
        }
    },
    "20": {
        "question": "Koji je glavni cilj primene metoda inverznog dizajna u dijamantskoj fotonici?",
        "options": {
            "A": "Smanjenje veličine uređaja",
            "B": "Poboljšanje električne provodljivosti",
            "C": "Prevazilaženje ograničenja izrade i razvoj efikasnih fotonskih krugova",
            "D": "Povećanje toplotne stabilnosti",
            "E": "Pojednostavljenje procesa dizajna"
        }
    }
}