{
    "1": {
        "question": "প্রবন্ধ 'Inverse-designed diamond photonics' এর প্রধান লক্ষ্য কী?",
        "options": {
            "A": "নতুন হীরার কাটিং কৌশলগুলির উন্নয়ন।",
            "B": "হীরার তাপীয় বৈশিষ্ট্যগুলি অন্বেষণ করা।",
            "C": "ইনভার্স ডিজাইন ব্যবহার করে ফোটোনিক সার্কিটে রঙ কেন্দ্রগুলি সংহত করা।",
            "D": "প্রাকৃতিক হীরার গঠনগুলি তদন্ত করা।",
            "E": "হীরার গহনা তৈরি।"
        }
    },
    "2": {
        "question": "কেন হীরা হোস্টগুলি কোয়ান্টাম গণনার জন্য প্রতিশ্রুতিশীল বলে বিবেচিত হয়?",
        "options": {
            "A": "তাদের নান্দনিক আকর্ষণের কারণে।",
            "B": "তাদের অ-পরিবাহী প্রকৃতির কারণে।",
            "C": "তাদের দীর্ঘ সংহতি সময়ের জন্য।",
            "D": "উচ্চ তাপ পরিবাহিতার কারণে।",
            "E": "কারণ তারা আলো কার্যকরভাবে প্রতিফলিত করে।"
        }
    },
    "3": {
        "question": "এই গবেষণার প্রসঙ্গে একটি ইনভার্স ডিজাইন পদ্ধতি কী জন্য ব্যবহৃত হয়?",
        "options": {
            "A": "নান্দনিক রত্নপাথরের ডিজাইন খুঁজে বের করতে।",
            "B": "ডিভাইস তৈরির প্রচলিত সীমাবদ্ধতাগুলি অতিক্রম করতে।",
            "C": "হীরার পালিশ কৌশলগুলি উন্নত করতে।",
            "D": "হীরার কঠোরতা পরিমাপ করতে।",
            "E": "হীরার ভার্চুয়াল রিয়েলিটি সিমুলেশন তৈরি করতে।"
        }
    },
    "4": {
        "question": "হীরা ফোটোনিক সার্কিটের প্রধান কোন চ্যালেঞ্জটি প্রবন্ধে সমাধান করা হয়েছে?",
        "options": {
            "A": "হীরা কাটিংয়ে দক্ষ শ্রমিকের অভাব।",
            "B": "প্রাকৃতিক হীরার সীমিত প্রাপ্যতা।",
            "C": "পাতলা হীরা ফিল্মের অপর্যাপ্ত গুণমান।",
            "D": "হীরার গহনার উচ্চ খরচ।",
            "E": "হীরা কণার বিম গঠন করতে অসুবিধা।"
        }
    },
    "5": {
        "question": "কোন তৈরির কৌশল হীরাতে ত্রিভুজাকার ক্রস-সেকশন তৈরি করে?",
        "options": {
            "A": "হোমোএপিট্যাক্সি বৃদ্ধি।",
            "B": "স্ট্যান্ডার্ড হীরা পালিশ।",
            "C": "বাল্ক হীরার কোণযুক্ত খোদাই।",
            "D": "কোয়াসি-আইসোট্রপিক খোদাই।",
            "E": "স্পুটারিং কৌশল।"
        }
    },
    "6": {
        "question": "হীরা প্রক্রিয়াকরণের সাম্প্রতিক উন্নয়নগুলি কী ধরনের ক্রস-সেকশনগুলির অনুমতি দেয়?",
        "options": {
            "A": "বাঁকা ক্রস-সেকশন।",
            "B": "ষড়ভুজাকার ক্রস-সেকশন।",
            "C": "ত্রিভুজাকার ক্রস-সেকশন।",
            "D": "আয়তাকার ক্রস-সেকশন।",
            "E": "গোলাকার ক্রস-সেকশন।"
        }
    },
    "7": {
        "question": "কোয়াসি-আইসোট্রপিক খোদাইয়ের সাথে সম্পর্কিত একটি চ্যালেঞ্জ কী?",
        "options": {
            "A": "রঙের স্যাচুরেশনে সীমাবদ্ধতা।",
            "B": "প্রাথমিক খোদাই গভীরতার কারণে সীমিত বৈশিষ্ট্যের আকার।",
            "C": "প্রক্রিয়াকরণের অতিরিক্ত খরচ।",
            "D": "ত্রিভুজাকার ত্রুটি তৈরি।",
            "E": "পৃষ্ঠ পালিশে অসুবিধা।"
        }
    },
    "8": {
        "question": "ফোটোনিক্সে ইনভার্স ডিজাইন পদ্ধতিগুলি কোন কারণে মনোযোগ আকর্ষণ করেছে?",
        "options": {
            "A": "ডিজাইনগুলির নান্দনিক চেহারা।",
            "B": "ডিজাইন প্রক্রিয়ার গতি।",
            "C": "তাদের প্রচলিত ডিজাইনের উপর শ্রেষ্ঠত্ব।",
            "D": "পদ্ধতিগুলির নতুনত্ব এবং অনন্যতা।",
            "E": "বাস্তবায়নের সরলতা এবং সহজতা।"
        }
    },
    "9": {
        "question": "গবেষকরা ইনভার্স-ডিজাইন করা পদ্ধতি ব্যবহার করে কী ধরনের ডিভাইস তৈরি করেছিলেন?",
        "options": {
            "A": "ব্রড-স্পেকট্রাম ফোটোনিক প্রিজম।",
            "B": "ভার্টিকাল কাপলার এবং ওয়েভগাইড-স্প্লিটার।",
            "C": "হীরা-আবৃত আয়না।",
            "D": "অপটিক্যাল কেবল।",
            "E": "আলো ছড়ানো ডিফিউজার।"
        }
    },
    "10": {
        "question": "গবেষণায় বর্ণিত ইনভার্স-ডিজাইন করা ভার্টিকাল কাপলারের একটি মূল বৈশিষ্ট্য কী?",
        "options": {
            "A": "এটির একটি ত্রিভুজাকার পদচিহ্ন রয়েছে।",
            "B": "এটি অতিরিক্ত টেপারিং বিভাগ প্রয়োজন।",
            "C": "এটির একটি 1.0 × 1.0 μm পদচিহ্ন রয়েছে।",
            "D": "এটি প্রচলিত কাপলারগুলির তুলনায় কম শক্তিশালী।",
            "E": "এটি শুধুমাত্র শূন্যস্থানে কাজ করে।"
        }
    },
    "11": {
        "question": "গবেষণায় ওয়েভগাইড-স্প্লিটারগুলির উদ্দেশ্য কী?",
        "options": {
            "A": "আলোকে একাধিক দিকে বিচ্ছুরিত করতে।",
            "B": "হীরার পৃষ্ঠ পালিশ করতে।",
            "C": "ন্যানোরেজোনেটরের জন্য ইন্টারফেস হিসাবে কাজ করতে।",
            "D": "শক্তিকে তাপে রূপান্তর করতে।",
            "E": "অ-তৈরিরযোগ্য বৈশিষ্ট্য তৈরি করতে।"
        }
    },
    "12": {
        "question": "গ্রেটিং কাপলারগুলিতে উচ্চ কাপলিং দক্ষতা অর্জনের জন্য প্রায়ই কী প্রয়োজন?",
        "options": {
            "A": "তিনটি অক্ষ বরাবর সমতা।",
            "B": "বাঁকা খোদাই কৌশল।",
            "C": "z-অক্ষ বরাবর অসমতা।",
            "D": "নির্দিষ্ট তাপমাত্রা নিয়ন্ত্রণ।",
            "E": "উপাদান খরচ কমানো।"
        }
    },
    "13": {
        "question": "কোন উপাদান প্ল্যাটফর্মটি অত্যাধুনিক কোয়ান্টাম অপটিক্স পরীক্ষাগুলিকে সমর্থন করে না?",
        "options": {
            "A": "সিলিকা সাবস্ট্রেটে হীরা পাতলা-ফিল্ম।",
            "B": "গ্রাফিন-কভার্ড সাবস্ট্রেট।",
            "C": "সিলিকন কার্বাইড-ভিত্তিক সাবস্ট্রেট।",
            "D": "ইট্রিয়াম অরথোভানাডেট কাঠামো।",
            "E": "পলিমারিক কম্পোজিট।"
        }
    },
    "14": {
        "question": "হীরা কোয়ান্টাম ফোটোনিক্সে কোন প্রচলিত পদ্ধতি ব্যবহার করা কঠিন?",
        "options": {
            "A": "রাসায়নিক বাষ্প জমা।",
            "B": "মনোলিথিক গাউসিয়ান কাপলিং।",
            "C": "প্রচলিত সমমিত কাপলিং।",
            "D": "টেপার্ড ফাইবার পদ্ধতি।",
            "E": "হাইব্রিড এলাকা হ্রাস।"
        }
    },
    "15": {
        "question": "ইনভার্স-ডিজাইন করা ভার্টিকাল কাপলারের অনুকরণ করা শীর্ষ দক্ষতা কত ছিল?",
        "options": {
            "A": "10%",
            "B": "25%",
            "C": "50%",
            "D": "70%",
            "E": "90%"
        }
    },
    "16": {
        "question": "তৈরির সীমাবদ্ধতা বিবেচনা করার পরে, ইনভার্স-ডিজাইন করা কাপলার কী দক্ষতা অর্জন করেছিল?",
        "options": {
            "A": "25%",
            "B": "30%",
            "C": "40%",
            "D": "50%",
            "E": "60%"
        }
    },
    "17": {
        "question": "737 nm-এ কাপলিং দক্ষতা অপ্টিমাইজ করার জন্য কোন রঙ কেন্দ্র লাইনে গবেষণাটি মনোযোগ দিয়েছে?",
        "options": {
            "A": "নাইট্রোজেন-শূন্যস্থান কেন্দ্র।",
            "B": "সিলিকন-শূন্যস্থান কেন্দ্র।",
            "C": "ক্রোমিয়াম-শূন্যস্থান কেন্দ্র।",
            "D": "টিন-শূন্যস্থান কেন্দ্র।",
            "E": "নিকেল-শূন্যস্থান কেন্দ্র।"
        }
    },
    "18": {
        "question": "পরীক্ষায় মেরুকরণ পরিবর্তন করার সময় পাওয়ারের কী হ্রাস দেখা গেছে?",
        "options": {
            "A": "তিনগুণ হ্রাস।",
            "B": "চারগুণ হ্রাস।",
            "C": "পাঁচগুণ হ্রাস।",
            "D": "ছয়গুণ হ্রাস।",
            "E": "কোন হ্রাস নেই।"
        }
    },
    "19": {
        "question": "গবেষণায় মাল্টিমোড ফাইবার (MMF) এর জন্য পরিমাপ করা শীর্ষ দক্ষতা কত?",
        "options": {
            "A": "15%",
            "B": "18.5%",
            "C": "21.5%",
            "D": "26.5%",
            "E": "30%"
        }
    },
    "20": {
        "question": "৩০টি তৈরি করা ডিভাইসের গড় দক্ষতা কীভাবে তুলনা করে?",
        "options": {
            "A": "10.2%",
            "B": "15.1%",
            "C": "19.3%",
            "D": "24.2%",
            "E": "28.5%"
        }
    },
    "21": {
        "question": "প্রবন্ধটি ভার্টিকাল কাপলারগুলির কর্মক্ষমতা পরিমাপ করতে কী ব্যবহার করে?",
        "options": {
            "A": "ইলেকট্রন মাইক্রোস্কোপ।",
            "B": "সুপারকন্ডাক্টিং ডিটেক্টর।",
            "C": "নিরবিচ্ছিন্ন-তরঙ্গ Ti:Sapphire লেজার।",
            "D": "অতিবেগুনী আলো উৎস।",
            "E": "সলিড-স্টেট লাইট-এমিটিং ডায়োড।"
        }
    },
    "22": {
        "question": "গহ্বর পরীক্ষায় নচ ডিভাইসগুলির তুলনায় ইনভার্স-ডিজাইন করা ভার্টিকাল কাপলার ব্যবহার করে একটি উল্লেখযোগ্য উন্নতি কী ছিল?",
        "options": {
            "A": "৩৫০ গুণের বেশি উন্নতি।",
            "B": "৪৫০ গুণের বেশি উন্নতি।",
            "C": "৫৫০ গুণের বেশি উন্নতি।",
            "D": "৬৫০ গুণের বেশি উন্নতি।",
            "E": "কোন উল্লেখযোগ্য উন্নতি নেই।"
        }
    },
    "23": {
        "question": "স্থগিত হীরা ফোটোনিক্সে কোন উপাদানটি একটি বড় চ্যালেঞ্জ সৃষ্টি করে?",
        "options": {
            "A": "ফাইবার-অপটিক নেটওয়ার্ক।",
            "B": "সিলিকা সাবস্ট্রেট।",
            "C": "ওয়েভগাইড-স্প্লিটার।",
            "D": "প্লাজমা ট্রিটমেন্ট।",
            "E": "ইলেকট্রনিক মডুলেশন।"
        }
    },
    "24": {
        "question": "পরীক্ষার সময় তৈরি করা গহ্বরগুলিতে রেজোন্যান্স কীভাবে টিউন করা হয়?",
        "options": {
            "A": "তাপীয় সম্প্রসারণ।",
            "B": "গ্যাস ঘনীভবন।",
            "C": "বৈদ্যুতিক ক্ষেত্র মডুলেশন।",
            "D": "রাসায়নিক প্রতিক্রিয়া।",
            "E": "অপটিক্যাল টুইজার।"
        }
    },
    "25": {
        "question": "একক ডিভাইসে একাধিক কার্যকারিতা একত্রিত করার মাধ্যমে কোন অ্যাপ্লিকেশন উপকৃত হতে পারে?",
        "options": {
            "A": "শক্তি সঞ্চয়।",
            "B": "ইলেকট্রনিক টিউনিং।",
            "C": "কোয়ান্টাম প্রযুক্তির স্কেলেবিলিটি।",
            "D": "যান্ত্রিক প্রকৌশল।",
            "E": "হাইড্রোজেন বন্ধন।"
        }
    },
    "26": {
        "question": "বৃহত্তর-স্কেল কোয়ান্টাম নেটওয়ার্ক দক্ষতার জন্য কোন দক্ষতা লক্ষ্য করা হয়?",
        "options": {
            "A": "৫০% এর নিচে দক্ষতা।",
            "B": "৬০% দক্ষতা।",
            "C": "৭০% দক্ষতা।",
            "D": "এককতার কাছাকাছি দক্ষতা।",
            "E": "১০০% এর উপরে দক্ষতা।"
        }
    },
    "27": {
        "question": "একটি সিমুলেশনে কাপলার দক্ষতা উন্নত করার একটি সম্ভাব্য পদ্ধতি কী?",
        "options": {
            "A": "জ্যামিতিক বিশ্বস্ততা হ্রাস করা।",
            "B": "লেজার স্পট আকার বৃদ্ধি করা।",
            "C": "ইলেকট্রন বিম লিথোগ্রাফি ব্যবহার করা।",
            "D": "ফোটোনিক ক্রিস্টাল ঘনত্ব হ্রাস করা।",
            "E": "তাপীয় ক্ষমতা বৃদ্ধি করা।"
        }
    },
    "28": {
        "question": "SiO2-এ আংশিক খোদাই এবং কাত করা ইনসিডেন্ট লেজার বিমের সাথে কী দক্ষতা অর্জন করা যেতে পারে?",
        "options": {
            "A": "৪০.৫%",
            "B": "৫১.০%",
            "C": "৫৬.৫%",
            "D": "৬৬.৫%",
            "E": "৭৬.৯%"
        }
    },
    "29": {
        "question": "মডেল ছাড়াই স্থগিত কাঠামো দিয়ে কী উন্নতি অর্জিত হয়?",
        "options": {
            "A": "৩৭.৯%",
            "B": "৪৭.২%",
            "C": "৫৭.৫%",
            "D": "৬৭.৯%",
            "E": "৭৭.৪%"
        }
    },
    "30": {
        "question": "স্থগিত হীরা সার্কিটে ফাইবার টেপার ব্যবহার করার একটি অসুবিধা কী?",
        "options": {
            "A": "ছোট ডিভাইসের পদচিহ্ন।",
            "B": "যান্ত্রিক অস্থিতিশীলতা।",
            "C": "বড় ডিভাইসের পদচিহ্ন।",
            "D": "খরচ নিষিদ্ধতা।",
            "E": "কম ফোটোনিক ঘনত্ব।"
        }
    },
    "31": {
        "question": "স্থগিত কাঠামোর জন্য ব্যাক-রিফ্লেক্টর ব্যবহার করে কোন অনুকরণ করা দক্ষতা মান অর্জিত হয়?",
        "options": {
            "A": "৬১.১%",
            "B": "৭২.৪%",
            "C": "৮১.০%",
            "D": "৮৬.৬%",
            "E": "৯০.৫%"
        }
    },
    "32": {
        "question": "সার্কিটে ইনভার্স ডিজাইনের ভূমিকা কী সীমাবদ্ধতার মধ্যে দক্ষতা সর্বাধিক করা?",
        "options": {
            "A": "একক পয়েন্ট পরিমাপ।",
            "B": "বিভিন্ন বায়ুমণ্ডলীয় চাপ।",
            "C": "তৈরি এবং কর্মক্ষমতা সীমাবদ্ধতা।",
            "D": "একক-উপাদান বিচ্ছিন্নতা।",
            "E": "অস্থায়ী সীমাবদ্ধতা।"
        }
    },
    "33": {
        "question": "এমন গবেষণায় একটি স্ক্যানিং ইলেকট্রন মাইক্রোগ্রাফ সাধারণত কী নির্দেশ করে?",
        "options": {
            "A": "ডিভাইস দক্ষতা।",
            "B": "মাইক্রোমিটার-স্কেল ভিজ্যুয়াল।",
            "C": "তাপীয় কর্মক্ষমতা।",
            "D": "রঙ বিতরণ।",
            "E": "অপটিক্যাল ঘনত্ব।"
        }
    },
    "34": {
        "question": "ইনভার্স-ডিজাইন করা ডিভাইসগুলি কোন ধরনের প্রচারের জন্য অপ্টিমাইজ করা হয়েছিল?",
        "options": {
            "A": "বৈদ্যুতিক পরিবাহিতা।",
            "B": "চৌম্বক ক্ষেত্রের সঙ্গতি।",
            "C": "TEM00 এবং TE মোড কাপলিং।",
            "D": "শারীরিক সহনশীলতা।",
            "E": "তাপীয় পরিবর্ধন।"
        }
    },
    "35": {
        "question": "এই পরীক্ষামূলক সেটআপগুলির প্রসঙ্গে PMF কী বোঝায়?",
        "options": {
            "A": "মেরুকরণ-পরিচালন ফাইবার।",
            "B": "ফোটন-বৃদ্ধি ফ্যাক্টর।",
            "C": "পিকো-মডুলেটিং ফাংশন।",
            "D": "ফেজ-ম্যাক্সিমাইজিং ফাইবার।",
            "E": "মেরুকরণ-রক্ষণাবেক্ষণ ফাইবার।"
        }
    },
    "36": {
        "question": "ফেজ-ম্যাচিংয়ের জন্য সার্কিটের বিভিন্ন পথ অপ্টিমাইজ করার জন্য গবেষণাটি কেন?",
        "options": {
            "A": "তরঙ্গ প্যাকেটের দৈর্ঘ্য কমাতে।",
            "B": "দৃশ্যত রঙ মেলাতে।",
            "C": "সঙ্গতিপূর্ণ সংকেত প্রক্রিয়াকরণ নিশ্চিত করতে।",
            "D": "গাণিতিক মডেলিং সহজ করতে।",
            "E": "জ্যামিতিক কাঠামো আকৃতি দিতে।"
        }
    },
    "37": {
        "question": "চ্যালেঞ্জিং তৈরির সত্ত্বেও কোন প্ল্যাটফর্মটি বিকল্প রুট হিসাবে হাইলাইট করা হয়েছে?",
        "options": {
            "A": "গ্লাস ফাইবার।",
            "B": "কোয়ান্টাম ডট।",
            "C": "সিলিকন কার্বাইড।",
            "D": "গ্রাফিন স্তর।",
            "E": "জার্মেনিয়াম ওয়েফার।"
        }
    },
    "38": {
        "question": "কাপলিং দক্ষতা সর্বাধিক করতে ডিভাইসগুলি কোন পরিবেশে স্থগিত করা হয়েছিল?",
        "options": {
            "A": "উচ্চ শূন্যস্থান।",
            "B": "বাতাসে স্থগিত।",
            "C": "জল নিমজ্জন।",
            "D": "গ্যাসীয় হিলিয়াম।",
            "E": "তরল নাইট্রোজেন।"
        }
    },
    "39": {
        "question": "MMF-এর জন্য পরীক্ষায় ব্রডব্যান্ড কর্মক্ষমতা কীভাবে চিহ্নিত করা হয়?",
        "options": {
            "A": "৮০ nm ব্যান্ডউইথ দ্বারা।",
            "B": "৯০ nm ব্যান্ডউইথ দ্বারা।",
            "C": "১০০ nm ব্যান্ডউইথ দ্বারা।",
            "D": "১১০ nm ব্যান্ডউইথ দ্বারা।",
            "E": "১২০ nm ব্যান্ডউইথ দ্বারা।"
        }
    },
    "40": {
        "question": "ভার্টিকালি সিমেট্রিক ডিজাইন কোন দক্ষতা মান অতিক্রম করতে পারে না?",
        "options": {
            "A": "৪০%",
            "B": "৫০%",
            "C": "৬০%",
            "D": "৭০%",
            "E": "৮০%"
        }
    },
    "41": {
        "question": "ইনভার্স ফোটোনিক ডিজাইনে, কোনটি মেরিটের চিত্র হিসাবে কাজ করে?",
        "options": {
            "A": "প্রতিফলন স্তর।",
            "B": "প্রতিসরণ সূচকের গুরুত্ব।",
            "C": "প্রাথমিক TE মোডে ইনসিডেন্ট আলো কাপলিং।",
            "D": "শারীরিক স্থায়িত্ব।",
            "E": "তরঙ্গ প্রশস্ততা ওঠানামা।"
        }
    },
    "42": {
        "question": "ডিজাইন সেটআপে 'ধূসর এলাকা' কী নির্দেশ করে?",
        "options": {
            "A": "প্রতিফলিত স্তর অঞ্চল।",
            "B": "ডিজাইন বাস্তবায়ন এলাকা।",
            "C": "উপযোগের জন্য মৃত এলাকা।",
            "D": "ফোটোনিক ক্রিস্টাল ফাঁকা।",
            "E": "পরিমাপের অযথার্থতা।"
        }
    },
    "43": {
        "question": "প্রবন্ধটি কোন বর্ণালী পরিসরে অসংখ্য ডিভাইস জুড়ে সংক্রমণ সাফল্য পর্যালোচনা করে?",
        "options": {
            "A": "৪০০-১০০০ nm।",
            "B": "৪৫০-৮৫০ nm।",
            "C": "৫০০-৭৫০ nm।",
            "D": "৫৫০-৮০০ nm।",
            "E": "৬০০-৯০০ nm।"
        }
    },
    "44": {
        "question": "ডিভাইস চরিত্রায়ণ পর্যায়ে, আউটপুট সনাক্ত করতে কোন পদ্ধতি ব্যবহার করা হয়?",
        "options": {
            "A": "সিঙ্গেল-মোড ফাইবার।",
            "B": "মাল্টিমোড ফাইবার।",
            "C": "আল্ট্রাসনিক সেন্সর।",
            "D": "উচ্চ-গতিশীল CCD।",
            "E": "ইনফ্রারেড লেজার।"
        }
    },
    "45": {
        "question": "ট্রান্সমিশন পরীক্ষাগুলি কোন কনফিগারেশনে কাপলার দক্ষতা পরিমাপ করে?",
        "options": {
            "A": "অর্ধ-কোণ প্রতিফলন।",
            "B": "সরাসরি সাবস্ট্রেট খোদাই।",
            "C": "ভার্টিকাল কাপলিং ইন্টারফেস।",
            "D": "ঘূর্ণিত অ্যারে মডেল।",
            "E": "সাইডলাইন ডিফ্রাকশন।"
        }
    },
    "46": {
        "question": "রঙ কেন্দ্রের কর্মক্ষমতা সামঞ্জস্য করতে কোন সংশোধনমূলক তৈরির কৌশলগুলি উল্লেখ করা হয়েছে?",
        "options": {
            "A": "কৌণিক টিল্ট।",
            "B": "হীরা পালিশ।",
            "C": "রেজোন্যান্সের জন্য গ্যাস টিউনিং।",
            "D": "রাসায়নিক আবরণ।",
            "E": "গঠন আকার পরিবর্তন।"
        }
    },
    "47": {
        "question": "ভার্টিকালি অসমমিত কাপলারগুলি কীভাবে ফাংশনগুলি উন্নত করতে সমতা ভঙ্গ করে?",
        "options": {
            "A": "অনুভূমিক নচ ব্যবহার করে।",
            "B": "আংশিক খোদাই ব্যবহার করে।",
            "C": "কৌণিক পেষণ দ্বারা।",
            "D": "ভেক্টর রঙ নির্দেশ করে।",
            "E": "হলোগ্রাফিক প্লেন বাঁকানো।"
        }
    },
    "48": {
        "question": "ব্যাক-রিফ্লেক্টর সহ স্থগিত হীরা কাঠামোর জন্য গবেষণাটি কোন অপ্টিমাইজ করা শর্ত অর্জন করেছে?",
        "options": {
            "A": "SiO2-এ ৭২.৪% দক্ষতা।",
            "B": "বাতাসে স্থগিত ৮১.২% দক্ষতা।",
            "C": "প্রতিফলক সহ বাতাসে স্থগিত ৮৬.৬% দক্ষতা।",
            "D": "টাইটানিয়াম আয়না সহ ৯৪.৩% দক্ষতা।",
            "E": "সম্পূর্ণ সমাধান সহ ১০০% দক্ষতা।"
        }
    },
    "49": {
        "question": "ফ্রি-স্পেস কাপলার দিয়ে কোন সম্ভাব্য উচ্চ-দক্ষতা সমাধান টেপারিং ফাইবারের তুলনায় সহজ?",
        "options": {
            "A": "বর্ণালী স্থানান্তর।",
            "B": "স্বতন্ত্র এমিটারগুলির অপটিক্যাল ড্রাইভিং।",
            "C": "মোডের তাপীয় দমন।",
            "D": "ইলেকট্রনিক ফাইবার নিয়ন্ত্রণ।",
            "E": "মাইক্রো-চৌম্বক স্পিন নিয়ন্ত্রণ।"
        }
    },
    "50": {
        "question": "পরবর্তী প্রজন্মের কোয়ান্টাম অপটিক্যাল পরীক্ষার ভিত্তি গঠন করে কোন মৌলিক কাজ?",
        "options": {
            "A": "নির্ভুল হীরা গহনা কাটিং।",
            "B": "ফোটোনিক সার্কিট পালস আকৃতি।",
            "C": "হীরা ফোটোনিক্সের জন্য ইনভার্স ডিজাইন অপ্টিমাইজেশন।",
            "D": "নমনীয় গ্লাস তৈরির।",
            "E": "কোয়ান্টাম রেজোন্যান্স সীমাবদ্ধতা।"
        }
    }
}