{
    "1": {
        "question": "Wat is de primaire methode die in deze studie wordt gebruikt om rek in 2D-halfgeleiders te bereiken?",
        "options": {
            "A": "Mechanische buiging",
            "B": "Chemische doping",
            "C": "Thermische uitzettingscoëfficiënt mismatch",
            "D": "Epitaxiale groei",
            "E": "Laserverwarming"
        }
    },
    "2": {
        "question": "Welk materiaal wordt in deze studie als modelsysteem gebruikt?",
        "options": {
            "A": "MoS2",
            "B": "WSe2",
            "C": "Grafeen",
            "D": "BN",
            "E": "SiO2"
        }
    },
    "3": {
        "question": "Welke reikwijdte van rek werd bereikt in de WSe2-monsters?",
        "options": {
            "A": "0,1% tot 0,5%",
            "B": "0,5% tot 1,0%",
            "C": "1% trek tot 0,2% druk",
            "D": "2% trek tot 1% druk",
            "E": "3% trek tot 2% druk"
        }
    },
    "4": {
        "question": "Wat is de betekenis van de indirect-naar-direct bandgapovergang die in de studie is waargenomen?",
        "options": {
            "A": "Het vermindert de thermische geleidbaarheid van het materiaal.",
            "B": "Het verbetert de mechanische sterkte van het materiaal.",
            "C": "Het verhoogt de optische emissie-efficiëntie van het materiaal.",
            "D": "Het vermindert de elektrische weerstand van het materiaal.",
            "E": "Het verbetert de chemische stabiliteit van het materiaal."
        }
    },
    "5": {
        "question": "Welk substraat wordt verwacht ontspannen WSe2-monsters te produceren vanwege zijn TCE?",
        "options": {
            "A": "Gesmolten silica",
            "B": "Aluminiumnitride",
            "C": "Saffier",
            "D": "Strontiumtitanaat",
            "E": "Silicium"
        }
    },
    "6": {
        "question": "Wat is de rol van de thermische uitzettingscoëfficiënt (TCE) in deze studie?",
        "options": {
            "A": "Om de elektrische eigenschappen van het substraat te bepalen",
            "B": "Om de rek in het 2D-materiaal te beheersen",
            "C": "Om de chemische reactiviteit van het materiaal te verbeteren",
            "D": "Om de optische transparantie van het substraat te verhogen",
            "E": "Om de thermische geleidbaarheid van het materiaal te verminderen"
        }
    },
    "7": {
        "question": "Welke techniek werd gebruikt om rek in de WSe2-monsters te kwantificeren?",
        "options": {
            "A": "Röntgendiffractie",
            "B": "Atomkrachtmicroscopie",
            "C": "Elektrondiffractie",
            "D": "Scanning tunneling microscopie",
            "E": "Fourier-transform infraroodspectroscopie"
        }
    },
    "8": {
        "question": "Wat is het effect van trekspanning op de PL-intensiteit van WSe2-monolagen bij lage temperaturen?",
        "options": {
            "A": "PL-intensiteit neemt af",
            "B": "PL-intensiteit blijft constant",
            "C": "PL-intensiteit neemt toe",
            "D": "PL-intensiteit fluctueert",
            "E": "PL-intensiteit wordt nul"
        }
    },
    "9": {
        "question": "Wat is het primaire voordeel van het gebruik van 2D TMDC's zoals WSe2 in opto-elektronica?",
        "options": {
            "A": "Hoge thermische geleidbaarheid",
            "B": "Aanwezigheid van een directe bandgap op de monolaaglimiet",
            "C": "Lage productiekosten",
            "D": "Hoge mechanische sterkte",
            "E": "Chemische inertheid"
        }
    },
    "10": {
        "question": "Wat is de betekenis van de Grüneisenparameter in deze studie?",
        "options": {
            "A": "Het meet de elektrische geleidbaarheid van het materiaal.",
            "B": "Het kwantificeert de thermische uitzetting van het substraat.",
            "C": "Het heeft betrekking op de Raman-piekverschuiving door rek.",
            "D": "Het bepaalt de optische transparantie van het materiaal.",
            "E": "Het geeft de chemische reactiviteit van het materiaal aan."
        }
    },
    "11": {
        "question": "Wat is de impact van snel afkoelen op de WSe2-monsters?",
        "options": {
            "A": "Het verhoogt de elektrische weerstand van het monster.",
            "B": "Het helpt de rek in het monster te behouden.",
            "C": "Het vermindert de optische emissie van het monster.",
            "D": "Het verbetert de thermische geleidbaarheid van het monster.",
            "E": "Het verandert de chemische samenstelling van het monster."
        }
    },
    "12": {
        "question": "Wat is het waargenomen effect van rek op het donkere exciton in WSe2-monolagen?",
        "options": {
            "A": "Donkere exciton energieniveau daalt",
            "B": "Donkere exciton energieniveau blijft onveranderd",
            "C": "Donkere exciton energieniveau stijgt",
            "D": "Donkere exciton wordt volledig gedoofd",
            "E": "Donkere exciton wordt stabieler"
        }
    },
    "13": {
        "question": "Welk substraat wordt verwacht drukspanning in WSe2 te induceren?",
        "options": {
            "A": "Gesmolten silica",
            "B": "Aluminiumnitride",
            "C": "Saffier",
            "D": "Strontiumtitanaat",
            "E": "Silicium"
        }
    },
    "14": {
        "question": "Wat is de primaire uitdaging bij het toepassen van traditionele rek-engineeringmethoden op 2D-materialen?",
        "options": {
            "A": "Hoge kosten van substraten",
            "B": "Zwakke interactie met substraten",
            "C": "Gebrek aan geschikte chemische precursoren",
            "D": "Onvermogen om hoge temperaturen te bereiken",
            "E": "Beperkte beschikbaarheid van 2D-materialen"
        }
    },
    "15": {
        "question": "Wat is het effect van de groeitemperatuur op de rek in WSe2-monolagen?",
        "options": {
            "A": "Hogere temperaturen verhogen de rek",
            "B": "Hogere temperaturen verminderen de rek",
            "C": "Temperatuur heeft geen effect op de rek",
            "D": "Rek is maximaal bij middelmatige temperaturen",
            "E": "Rek is minimaal bij middelmatige temperaturen"
        }
    },
    "16": {
        "question": "Wat is de rol van KBr in het CVD-groeiproces?",
        "options": {
            "A": "Het fungeert als een katalysator voor de reactie.",
            "B": "Het dient als promotor voor groei.",
            "C": "Het levert een bron van broom voor doping.",
            "D": "Het stabiliseert het substraatoppervlak.",
            "E": "Het verbetert de thermische geleidbaarheid van het substraat."
        }
    },
    "17": {
        "question": "Wat is de primaire reden voor het gebruik van elektrondiffractie in deze studie?",
        "options": {
            "A": "Om de optische eigenschappen van WSe2 te meten",
            "B": "Om de chemische samenstelling van WSe2 te bepalen",
            "C": "Om de rek in WSe2 te kwantificeren",
            "D": "Om de thermische eigenschappen van WSe2 te analyseren",
            "E": "Om de oppervlakte morfologie van WSe2 te bestuderen"
        }
    },
    "18": {
        "question": "Wat is het waargenomen effect van rek op de PL-piekpositie van WSe2?",
        "options": {
            "A": "PL-piekpositie verschuift naar hogere energie",
            "B": "PL-piekpositie verschuift naar lagere energie",
            "C": "PL-piekpositie blijft onveranderd",
            "D": "PL-piekpositie wordt breder",
            "E": "PL-piekpositie wordt smaller"
        }
    },
    "19": {
        "question": "Wat is de betekenis van de indirect-naar-direct bandgapovergang in bilayer WSe2?",
        "options": {
            "A": "Het vermindert de thermische uitzetting van het materiaal.",
            "B": "Het verhoogt de optische absorptie van het materiaal.",
            "C": "Het verbetert de mechanische flexibiliteit van het materiaal.",
            "D": "Het verbetert de elektrische geleidbaarheid van het materiaal.",
            "E": "Het verhoogt de fotoluminescentie-intensiteit van het materiaal."
        }
    },
    "20": {
        "question": "Wat is de primaire conclusie van de studie met betrekking tot rek-engineering in 2D-materialen?",
        "options": {
            "A": "Rek-engineering is niet haalbaar in 2D-materialen.",
            "B": "Rek-engineering kan alleen worden bereikt door mechanische buiging.",
            "C": "Rek-engineering maakt modulatie van 2D-materiaaleigenschappen mogelijk.",
            "D": "Rek-engineering is beperkt tot kleinschalige toepassingen.",
            "E": "Rek-engineering heeft geen effect op 2D-materiaaleigenschappen."
        }
    }
}