{
    "1": {
        "question": "సెమీకండక్టర్లకు ఒత్తిడి పెట్టడం యొక్క ప్రధాన ఉద్దేశ్యం ఏమిటి?",
        "options": {
            "A": "వాటి రంగును మార్చడానికి.",
            "B": "వాటి బ్యాండ్ నిర్మాణాన్ని మార్చడానికి.",
            "C": "వాటి ఉష్ణోగ్రతను తగ్గించడానికి.",
            "D": "వాటి బరువును పెంచడానికి.",
            "E": "విద్యుత్ ఉత్పత్తి చేయడానికి."
        }
    },
    "2": {
        "question": "సాంప్రదాయ ఒత్తిడి ఇంజనీరింగ్ 2D సెమీకండక్టర్లకు ఎందుకు సాధ్యం కాదు?",
        "options": {
            "A": "వాటిని ఒత్తిడి చేయడానికి అవి చాలా మందంగా ఉంటాయి.",
            "B": "వాటికి బ్యాండ్ నిర్మాణం ఉండదు.",
            "C": "వాటికి సాధారణంగా ఉపరితలంతో ఎపిటాక్సియల్ పరస్పర చర్య ఉండదు.",
            "D": "వాటిని చల్లబరచలేము.",
            "E": "వాటికి విద్యుత్ వాహకత ఉండదు."
        }
    },
    "3": {
        "question": "2D సెమీకండక్టర్ల ఒత్తిడి ఇంజనీరింగ్ కోసం వ్యాసంలో ఏ పద్ధతిని ప్రదర్శించారు?",
        "options": {
            "A": "బలమైన విద్యుత్ క్షేత్రాన్ని ఉపయోగించడం.",
            "B": "చుంబక శక్తిని ఉపయోగించడం.",
            "C": "విస్తరణ అసమానత యొక్క ఉష్ణ గుణకాన్ని ఉపయోగించడం.",
            "D": "పీడనాన్ని మార్చడం.",
            "E": "లేజర్ పల్సులతో ప్రకాశించడం."
        }
    },
    "4": {
        "question": "అధ్యయనంలో మోడల్ సిస్టమ్‌గా ఏ పదార్థాన్ని ఉపయోగించారు?",
        "options": {
            "A": "గ్రాఫీన్",
            "B": "MoS2",
            "C": "WSe2",
            "D": "SiC",
            "E": "Al2O3"
        }
    },
    "5": {
        "question": "వివిధ ఉష్ణ గుణకాల విస్తరణతో ఉపరితలాలపై WSe2లో సాధించగల ఒత్తిడి పరిధి ఏమిటి?",
        "options": {
            "A": "1% టెన్సైల్ నుండి 0.2% కాంప్రెసివ్",
            "B": "2% టెన్సైల్ నుండి 0.5% కాంప్రెసివ్",
            "C": "0.5% టెన్సైల్ నుండి 1% కాంప్రెసివ్",
            "D": "3% టెన్సైల్ నుండి 1% కాంప్రెసివ్",
            "E": "0.1% టెన్సైల్ నుండి 2% కాంప్రెసివ్"
        }
    },
    "6": {
        "question": "టెన్సైల్ ఒత్తిడిలో బిలేయర్ WSe2లో ఏ ఆప్టికల్ ట్రాన్సిషన్ గమనించబడింది?",
        "options": {
            "A": "డైరెక్ట్-టు-ఇండైరెక్ట్ బ్యాండ్ గ్యాప్ ట్రాన్సిషన్",
            "B": "మెటల్-టు-ఇన్సులేటర్ ట్రాన్సిషన్",
            "C": "ఇండైరెక్ట్-టు-డైరెక్ట్ బ్యాండ్ గ్యాప్ ట్రాన్సిషన్",
            "D": "డైరెక్ట్-టు-మెటల్ ట్రాన్సిషన్",
            "E": "సూపర్‌కండక్టర్ దశ మార్పు"
        }
    },
    "7": {
        "question": "ఈ అధ్యయనంలో, పెద్ద ఉష్ణ గుణకాల విస్తరణ అసమానత ఏమి చేస్తుంది?",
        "options": {
            "A": "ఏకరీతి స్ఫటిక వృద్ధి.",
            "B": "నానోవైర్లు ఉత్పత్తి.",
            "C": "2D పదార్థంలో నియంత్రిత ఒత్తిడి.",
            "D": "ఆప్టికల్ పనితీరును తగ్గిస్తుంది.",
            "E": "ఎలక్ట్రానిక్ లక్షణాల నష్టం."
        }
    },
    "8": {
        "question": "2D ట్రాన్సిషన్ మెటల్ డైచాల్కోజెనైడ్స్ (TMDCs) కోసం ఒత్తిడి ఇంజనీరింగ్ ఎందుకు ముఖ్యమైనది?",
        "options": {
            "A": "వాటిని మెరుగైన విద్యుత్ వాహకత కలిగిస్తుంది.",
            "B": "వాటిని తేలికగా చేస్తుంది.",
            "C": "వాటి ఆప్టోఎలక్ట్రానిక్ లక్షణాలను సర్దుబాటు చేస్తుంది.",
            "D": "వాటి పరిమాణాన్ని పెంచుతుంది.",
            "E": "వాటిని ఇన్సులేటర్లుగా మారుస్తుంది."
        }
    },
    "9": {
        "question": "అనుసంధానంలో ఒత్తిడిని ఎలా లక్షణీకరించారు?",
        "options": {
            "A": "ఎక్స్-రే డిఫ్రాక్షన్ ఉపయోగించి.",
            "B": "ఎలక్ట్రాన్ డిఫ్రాక్షన్ మరియు రమన్ స్పెక్ట్రోస్కోపీ ఉపయోగించి.",
            "C": "రసాయన విశ్లేషణ ఉపయోగించి.",
            "D": "బరువు కొలతలు ఉపయోగించి.",
            "E": "అణు శోషణ స్పెక్ట్రోస్కోపీ ఉపయోగించి."
        }
    },
    "10": {
        "question": "మోనోలేయర్ WSe2లో ఒత్తిడితో ఏ ఘటనం నియంత్రించబడింది?",
        "options": {
            "A": "కరిగే స్థానం",
            "B": "డార్క్ ఎక్సిటాన్ క్వెంచింగ్",
            "C": "చుంబక లక్షణాలు",
            "D": "విద్యుత్ నిరోధకత",
            "E": "అయనీకరణ శక్తి"
        }
    },
    "11": {
        "question": "అధ్యయనంలో ఒత్తిడిని పరిమాణపరచడానికి ఏ పద్ధతులను పోల్చారు?",
        "options": {
            "A": "విసరణ మరియు ఆవిరి వేగాలు.",
            "B": "రమన్ షిఫ్ట్ మరియు లాటిస్ స్థిరాంక కొలత.",
            "C": "ఎక్స్-రే ఫ్లోరెసెన్స్ మరియు సహన స్థాయిలు.",
            "D": "పౌడర్ డిఫ్రాక్షన్ మరియు వేడి సామర్థ్యం.",
            "E": "దశ మార్పు ఉష్ణోగ్రత మరియు సాంద్రత."
        }
    },
    "12": {
        "question": "WSe2 కంటే చిన్న TCE ఉన్న ఉపరితలం WSe2లో ఒత్తిడిని ఎలా ప్రభావితం చేస్తుంది?",
        "options": {
            "A": "ఇది టెన్సైల్ ఒత్తిడిని సృష్టిస్తుంది.",
            "B": "ఇది కాంప్రెసివ్ ఒత్తిడిని సృష్టిస్తుంది.",
            "C": "ఇది ఒత్తిడిని సృష్టించదు.",
            "D": "ఇది WSe2ని కరిగిస్తుంది.",
            "E": "ఇది WSe2ని పగలగొడుతుంది."
        }
    },
    "13": {
        "question": "కొత్త ఉపరితలానికి బదిలీ చేసినప్పుడు WSe2 ఉద్గారానికి ఏమి జరుగుతుంది?",
        "options": {
            "A": "దీని తీవ్రత పెరుగుతుంది.",
            "B": "ఇది కొత్త రంగులను పొందుతుంది.",
            "C": "ఇది ఎక్కువ శక్తి స్థితికి మారుతుంది.",
            "D": "ఇది తొలగించిన నమూనాల వంటి దానిగా మారుతుంది.",
            "E": "ఇది కనిపించకుండా పోతుంది."
        }
    },
    "14": {
        "question": "2D పదార్థాలలో TCE-అసమానత కారణంగా ఒత్తిడిని నిలుపుకోవడానికి కీలకమైన ఉపరితల లక్షణం ఏమిటి?",
        "options": {
            "A": "ఉపరితలం లోహంగా ఉండాలి.",
            "B": "ఉపరితలం చాలా మృదువుగా ఉండాలి.",
            "C": "ఉపరితలం వంకరగా ఉండాలి.",
            "D": "ఉపరితలం అమోర్ఫస్‌గా ఉండాలి.",
            "E": "TCE తేడా లేనట్టే ఉంటుంది."
        }
    },
    "15": {
        "question": "అనుసంధానంలో పెద్ద ప్రాంతం ఉన్న ఒత్తిడి 2D సెమీకండక్టర్లను పొందడానికి ఏ ప్రయోగాత్మక సాంకేతికతను ఉపయోగించారు?",
        "options": {
            "A": "పల్స్డ్ లేజర్ డిపాజిషన్.",
            "B": "రసాయన ఆవిరి డిపాజిషన్ (CVD) TCE అసమానతను ఉపయోగించి.",
            "C": "ద్రవ దశ నుండి కాస్టింగ్.",
            "D": "అయాన్ ఇంప్లాంటేషన్.",
            "E": "మాగ్నెట్రాన్ స్పట్టరింగ్."
        }
    },
    "16": {
        "question": "సింథసిస్ తర్వాత WSe2 నమూనాలలో ఒత్తిడిని నిర్వహించడానికి ఏ అంశం ముఖ్యమైనదిగా కనుగొన్నారు?",
        "options": {
            "A": "మందగించిన కూలింగ్ ప్రక్రియ.",
            "B": "రసాయన స్థిరీకరణాలను ఉపయోగించడం.",
            "C": "వేగవంతమైన క్వెంచింగ్ ప్రక్రియ.",
            "D": "విద్యుత్ ఉద్దీపన.",
            "E": "హైడ్రోజన్ వాయువు పరిచయం."
        }
    },
    "17": {
        "question": "ప్రయోగాలలో, ఏ ఉపరితలం విశ్రాంత WSe2 నమూనాలను ఉత్పత్తి చేయడానికి ఆశించబడుతుంది?",
        "options": {
            "A": "ఫ్యూజ్డ్ సిలికా",
            "B": "సఫైర్",
            "C": "స్ట్రాంటియం టైటానేట్ (STO)",
            "D": "అల్యూమినియం నైట్రైడ్ (AlN)",
            "E": "సిలికాన్ కార్బైడ్"
        }
    },
    "18": {
        "question": "2D పదార్థాలలో ఒత్తిడి ఇంజనీరింగ్ ద్వారా ప్రత్యేకంగా నియంత్రించబడే భౌతిక లక్షణం ఏమిటి?",
        "options": {
            "A": "యాంత్రిక బలం",
            "B": "ఉష్ణ స్థిరత్వం",
            "C": "ఎలక్ట్రానిక్ బ్యాండ్ నిర్మాణం",
            "D": "తుప్పు నిరోధకత",
            "E": "అణు ద్రవ్యం"
        }
    },
    "19": {
        "question": "WSe2 యొక్క రమన్ E' పీక్‌కు ఒత్తిడి పెట్టినప్పుడు ఏమి మార్పు జరుగుతుంది?",
        "options": {
            "A": "ఇది ఫ్రీక్వెన్సీలో పైకి మారుతుంది.",
            "B": "ఇది పూర్తిగా మాయమవుతుంది.",
            "C": "ఇది మార్పు చెందదు.",
            "D": "ఇది గణనీయంగా విస్తరించబడుతుంది.",
            "E": "ఇది ఫ్రీక్వెన్సీలో క్రిందికి మారుతుంది."
        }
    },
    "20": {
        "question": "WSe2లో ఇండైరెక్ట్-టు-డైరెక్ట్ బ్యాండ్ గ్యాప్ మార్పు యొక్క ప్రాముఖ్యత ఏమిటి?",
        "options": {
            "A": "పరికరాలలో విద్యుత్ వినియోగాన్ని తగ్గిస్తుంది.",
            "B": "పారదర్శక ఎలక్ట్రానిక్స్‌ను సాధ్యం చేస్తుంది.",
            "C": "ఆప్టికల్ శోషణ సామర్థ్యాన్ని పెంచుతుంది.",
            "D": "ఉష్ణ వాహకతను మెరుగుపరుస్తుంది.",
            "E": "ఫ్లోరెసెన్స్ అందిస్తుంది."
        }
    },
    "21": {
        "question": "అధ్యయన ప్రకారం, ఒత్తిడిలో మోనోలేయర్ WSe2లో డార్క్ ఎక్సిటాన్లు ఎలా ప్రవర్తిస్తాయి?",
        "options": {
            "A": "వాటిని ఒత్తిడి కింద మాయమవుతాయి.",
            "B": "వాటిని ప్రకాశవంతంగా మారతాయి.",
            "C": "వాటిని రెండు ప్రత్యేక పీక్‌లుగా విభజిస్తాయి.",
            "D": "వాటిని శక్తి తగ్గుతుంది.",
            "E": "వాటిని ఒత్తిడి నష్టానికి కారణమవుతాయి."
        }
    },
    "22": {
        "question": "అధ్యయన ప్రకారం, టెన్సైల్ ఒత్తిడికి అనుగుణంగా రమన్ స్పెక్ట్రాలో ఏ పీక్ మార్పు గమనించబడింది?",
        "options": {
            "A": "0.5 cm⁻¹",
            "B": "1.5 cm⁻¹",
            "C": "3.0 cm⁻¹",
            "D": "2.0 cm⁻¹",
            "E": "4.0 cm⁻¹"
        }
    },
    "23": {
        "question": "WSe2లో ఒత్తిడిని సాధించడానికి ఉపరితలం యొక్క ఏ లక్షణాన్ని నియంత్రిస్తారు?",
        "options": {
            "A": "రసాయన కూర్పు",
            "B": "యాంత్రిక దృఢత్వం",
            "C": "ఉష్ణ గుణకం విస్తరణ",
            "D": "చుంబక పారగమ్యత",
            "E": "విద్యుత్ నిరోధకత"
        }
    },
    "24": {
        "question": "అనుసంధానంలో ఎలక్ట్రాన్ డిఫ్రాక్షన్ ఎందుకు ఉపయోగించబడింది?",
        "options": {
            "A": "నమూనా పరిమాణాన్ని పెంచడానికి.",
            "B": "రసాయన బంధాలను చూడటానికి.",
            "C": "లాటిస్ స్థిరాంకాన్ని కొలవడానికి మరియు ఒత్తిడిని పరిమాణపరచడానికి.",
            "D": "ఎలక్ట్రోమాగ్నెటిక్ షీల్డింగ్ అందించడానికి.",
            "E": "నమూనాలపై ఒత్తిడి పెట్టడానికి."
        }
    },
    "25": {
        "question": "2D పదార్థాల వృద్ధిలో వాన్ డెర్ వాల్స్ పరస్పర చర్య ఏ సవాలు కలిగిస్తుంది?",
        "options": {
            "A": "ఇది అధిక ఒత్తిడిని అందిస్తుంది.",
            "B": "ఇది అనవసర రసాయన ప్రతిచర్యలను కలిగిస్తుంది.",
            "C": "ఇది పెద్ద ఒత్తిడులను నిలుపుకోవడం కష్టతరం చేస్తుంది.",
            "D": "ఇది విద్యుత్ అస్థిరతకు దారితీస్తుంది.",
            "E": "ఇది ఉష్ణ నష్టాలను పెంచుతుంది."
        }
    },
    "26": {
        "question": "CVD ప్రక్రియలో WSe2 వృద్ధిని ప్రారంభించేది ఏమిటి?",
        "options": {
            "A": "చుంబక క్షేత్రాన్ని జోడించడం",
            "B": "హైడ్రోజన్ పరిచయం",
            "C": "ఉపరితల పీడనాన్ని పెంచడం",
            "D": "భట్టిని చల్లబరచడం",
            "E": "వాక్యూమ్ పరిస్థితులను వర్తింపజేయడం"
        }
    },
    "27": {
        "question": "WSe2 సింథసిస్‌లో వేగవంతమైన క్వెంచింగ్ ఎందుకు ముఖ్యమైనది?",
        "options": {
            "A": "వృద్ధి వేగాన్ని పెంచడానికి.",
            "B": "స్ఫటిక లాటిస్‌ను ఘనీకరించడానికి.",
            "C": "ఒత్తిడి విశ్రాంతిని నివారించడానికి.",
            "D": "ఏకరీతి లేయరింగ్‌ను నిర్ధారించడానికి.",
            "E": "ఎలక్ట్రాన్ మొబిలిటీని మెరుగుపరచడానికి."
        }
    },
    "28": {
        "question": "ఫ్యూజ్డ్ సిలికాపై పెరిగిన WSe2 నమూనాల సాధారణ క్వాంటం దిగుబడి ఎంత?",
        "options": {
            "A": "5.0%",
            "B": "10.0%",
            "C": "2.3%",
            "D": "0.5%",
            "E": "0.1%"
        }
    },
    "29": {
        "question": "ppm K⁻¹కు ఒత్తిడి యొక్క సూత్రపూర్వక విలువ ఏదికి దగ్గరగా ఉంటుంది?",
        "options": {
            "A": "-0.05%",
            "B": "-0.09%",
            "C": "-0.20%",
            "D": "-0.15%",
            "E": "-0.30%"
        }
    },
    "30": {
        "question": "2D పదార్థాలలో కొత్త ఒత్తిడి ఇంజనీరింగ్ పద్ధతితో పరిష్కరించిన ప్రధాన సవాలు ఏమిటి?",
        "options": {
            "A": "విద్యుత్ నిరోధకతను పెంచడం.",
            "B": "ఉష్ణ విస్తరణలో అసమానత లేకుండా ఒత్తిడిని సాధించడం.",
            "C": "ఏకరీతి టెన్సైల్ మరియు కాంప్రెసివ్ ఒత్తిడులను సృష్టించడం.",
            "D": "రసాయన ఆవిరి డిపాజిషన్ ఉపయోగాన్ని నివారించడం.",
            "E": "మొత్తం పదార్థం మందాన్ని తగ్గించడం."
        }
    },
    "31": {
        "question": "తక్కువ ఉష్ణోగ్రతకు తగ్గించడం టెన్సైల్ ఒత్తిడితో ఉన్న మోనోలేయర్ WSe2 యొక్క ఫోటోల్యూమినెసెన్స్‌ను ఎలా ప్రభావితం చేస్తుంది?",
        "options": {
            "A": "PL తీవ్రత తగ్గుతుంది.",
            "B": "PL తీవ్రత పెరుగుతుంది.",
            "C": "PL తీవ్రతలో మార్పు ఉండదు.",
            "D": "ఇది తక్షణ క్వెంచింగ్‌కు దారితీస్తుంది.",
            "E": "PL గుర్తించలేనిది అవుతుంది."
        }
    },
    "32": {
        "question": "ఇండైరెక్ట్-టు-డైరెక్ట్ బ్యాండ్ గ్యాప్ మార్పు ఎందుకు ముఖ్యమైనది?",
        "options": {
            "A": "మైక్రోవేవ్ అనువర్తనాలలో ఉపయోగాన్ని అనుమతిస్తుంది.",
            "B": "ఉష్ణ వాహకతను పెంచుతుంది.",
            "C": "ఫోటోల్యూమినెసెన్స్ సామర్థ్యాన్ని పెంచుతుంది.",
            "D": "పదార్థం యొక్క సాంద్రతను తగ్గిస్తుంది.",
            "E": "పదార్థాలకు లోహపు మెరుపును ఇస్తుంది."
        }
    },
    "33": {
        "question": "PL క్వాంటం దిగుబడిని ఆప్టిమైజ్ చేయడానికి CVD వృద్ధిలో ఏ పరిస్థితులను నియంత్రించారు?",
        "options": {
            "A": "ఉపరితల వెడల్పు మరియు పొడవు.",
            "B": "హైడ్రోజన్/ఆర్గాన్ నిష్పత్తి మరియు వృద్ధి సమయం.",
            "C": "లేజర్ తీవ్రత మరియు తరంగదైర్ఘ్యం.",
            "D": "చుంబక క్షేత్ర బలం.",
            "E": "ఉపరితల విద్యుత్ వాహకత."
        }
    },
    "34": {
        "question": "ప్రదర్శించిన దానికంటే పెద్ద ఒత్తిడుల కోసం, వ్యాసం ప్రకారం ఏ రకమైన ఉపరితలాలను పరిగణించవచ్చు?",
        "options": {
            "A": "బలమైన ఉపరితల ఆంకరింగ్ ఉన్న ఉపరితలాలు.",
            "B": "ఐసోట్రోపిక్ ఉష్ణ విస్తరణ ఉన్న ఉపరితలాలు.",
            "C": "పియెజోఎలక్ట్రిక్ ఉపరితలాలు.",
            "D": "లోహపరచిన ఉపరితలాలు.",
            "E": "ప్రతిచర్య ఉపరితలాలు."
        }
    },
    "35": {
        "question": "ఒత్తిడి మరియు ఒత్తిడి లేని WSe2 లాటిస్ స్థిరాంకాలను నేరుగా కొలవడానికి ఏ పద్ధతి అనుమతించింది?",
        "options": {
            "A": "ఎక్స్-రే డిఫ్రాక్షన్.",
            "B": "SiO2 మెంబ్రేన్‌లపై ఎలక్ట్రాన్ డిఫ్రాక్షన్.",
            "C": "అణు శోషణ స్పెక్ట్రోస్కోపీ.",
            "D": "ఎలక్ట్రోస్టాటిక్స్ విశ్లేషణ.",
            "E": "మాగ్నెటిక్ రెసోనెన్స్ ఇమేజింగ్."
        }
    },
    "36": {
        "question": "TCE అంటే ఏమిటి?",
        "options": {
            "A": "ఉష్ణ గుణకం విస్తరణ",
            "B": "ట్యూన్డ్ కెమికల్ ఎనర్జీ",
            "C": "సూత్రపూర్వక రసాయన మూలకం",
            "D": "ఉష్ణ వాహకత శక్తి",
            "E": "టోనిక్ కేటియన్ ఎక్స్చేంజ్"
        }
    },
    "37": {
        "question": "ఆప్టోఎలక్ట్రానిక్ అనువర్తనాలలో డార్క్ ఎక్సిటాన్ క్వెంచింగ్ ఎందుకు ముఖ్యమైనది?",
        "options": {
            "A": "ఇది గామా తరంగాలను గుర్తించడానికి అనుమతిస్తుంది.",
            "B": "ఇది పదార్థాలను పారదర్శకంగా చేస్తుంది.",
            "C": "ఇది పరికర పనితీరును మెరుగుపరచడంలో సహాయపడుతుంది.",
            "D": "ఇది రేడియో తరంగ శోషణను సాధ్యం చేస్తుంది.",
            "E": "ఇది ఉష్ణ విస్తరణను తగ్గిస్తుంది."
        }
    },
    "38": {
        "question": "WSe2 యొక్క ఫోటోల్యూమినెసెన్స్ సామర్థ్యాన్ని కొలవడానికి ఏ ప్రయోగాత్మక సాంకేతికతను ఉపయోగించారు?",
        "options": {
            "A": "మైక్రోస్కేల్ కెమిస్ట్రీ విశ్లేషణ",
            "B": "అల్ట్రాసోనిక్ వైబ్రేషనల్ టెస్టింగ్",
            "C": "మైక్రో-PL ఇన్‌స్ట్రుమెంటేషన్",
            "D": "ఎలక్ట్రాన్ స్పిన్ రెసోనెన్స్",
            "E": "ధ్రువీకృత కాంతి చెల్లాచెదురు"
        }
    },
    "39": {
        "question": "బదిలీ చేసిన WSe2 నమూనాలు తొలగించిన WSe2 నమూనాలకు ఎలా సమానంగా ప్రవర్తించాయి?",
        "options": {
            "A": "వాటిని ఉష్ణ వాహకత పెరిగింది.",
            "B": "వాటిని సమాన ఉద్గార పీక్ చూపించాయి.",
            "C": "వాటిని భిన్నమైన స్ఫటిక నిర్మాణం అభివృద్ధి చెందింది.",
            "D": "వాటికి ఎక్కువ TCE ఉంది.",
            "E": "వాటిని అన్ని ల్యూమినెసెన్స్ కోల్పోయాయి."
        }
    },
    "40": {
        "question": "అనుసంధానంలో గమనించినట్లుగా మోలార్ శాతం లో లెక్కించిన ఒత్తిడులు ఏమిటి?",
        "options": {
            "A": "5% కాంప్రెసివ్ - 2% టెన్సైల్",
            "B": "0% కాంప్రెసివ్ - 10% టెన్సైల్",
            "C": "0.2% కాంప్రెసివ్ - 1% టెన్సైల్",
            "D": "8% కాంప్రెసివ్ - 3% టెన్సైల్",
            "E": "1.5% కాంప్రెసివ్ - 2.5% టెన్సైల్"
        }
    },
    "41": {
        "question": "రసాయన ఆవిరి డిపాజిషన్ ప్రక్రియలో WSe2 వృద్ధికి ప్రమోటర్‌గా ఏమి ఉపయోగించారు?",
        "options": {
            "A": "గ్రాఫైట్",
            "B": "పొటాషియం బ్రోమైడ్ (KBr)",
            "C": "కేల్షియం క్లోరైడ్",
            "D": "సోడియం అసిటేట్",
            "E": "కాపర్ సల్ఫేట్"
        }
    },
    "42": {
        "question": "ఒత్తిడి ఇంప్లాంటింగ్ సమయంలో, WSe2 కంటే ఎక్కువ TCE ఉన్న ఉపరితలం ఏ రకమైన ఒత్తిడిని ఉత్పత్తి చేస్తుంది?",
        "options": {
            "A": "న్యూట్రల్ ఒత్తిడి.",
            "B": "షీర్ ఒత్తిడి.",
            "C": "దిశాత్మక ఒత్తిడి.",
            "D": "కాంప్రెసివ్ ఒత్తిడి.",
            "E": "ఏ ఒత్తిడిని ఉత్పత్తి చేయదు."
        }
    },
    "43": {
        "question": "తక్కువ ఉష్ణోగ్రతలలో టెన్సైల్ ఒత్తిడితో ఉన్న మోనోలేయర్ WSe2లో ఏ PL ప్రవర్తన గమనించబడింది?",
        "options": {
            "A": "ఉద్గారాల సంతృప్తి.",
            "B": "అరాడియేటివ్ స్థితులకు క్షీణత.",
            "C": "ఫోటోల్యూమినెసెన్స్‌లో గణనీయమైన పెరుగుదల.",
            "D": "గణనీయమైన మార్పు లేదు.",
            "E": "ఉద్గార పీక్ యొక్క నీలి మార్పు."
        }
    },
    "44": {
        "question": "సూత్రపూర్వక విలువలతో పోలిస్తే ΔTCEకు గణనాత్మక ప్రయోగాత్మక ఒత్తిడి ఎలా ఉంటుంది?",
        "options": {
            "A": "ఇది ఊహించిన దానికంటే రెండుసార్లు ఎక్కువ.",
            "B": "ఇది ఊహించిన దాని సగం.",
            "C": "ఇది సిద్ధాంతంతో అద్భుతమైన ఒప్పందంలో ఉంది.",
            "D": "ఇది ఊహించిన దానికంటే పది రెట్లు తక్కువ.",
            "E": "ఇది సిద్ధాంతానికి పూర్తిగా వ్యతిరేకంగా ఉంది."
        }
    },
    "45": {
        "question": "వివిధ ఉపరితలాలకు WSe2ని బదిలీ చేసినప్పుడు, PL పీక్‌ల గురించి ఏ పరిశీలన చేయబడింది?",
        "options": {
            "A": "PL పీక్ అనేక ఉప పీక్‌లుగా విభజించబడుతుంది.",
            "B": "PL పీక్ మార్పు చెందలేదు.",
            "C": "PL పీక్ విస్తరించి కానీ తీవ్రంగా మారుతుంది.",
            "D": "PL పీక్ పూర్తిగా మాయమవుతుంది.",
            "E": "PL పీక్ పెద్ద తరంగదైర్ఘ్యానికి మారుతుంది."
        }
    },
    "46": {
        "question": "2D పదార్థాలను ఒత్తిడి చేయడానికి ఉపరితలానికి అవసరమైన ముఖ్యమైన లక్షణం ఏమిటి?",
        "options": {
            "A": "అత్యంత విద్యుత్ వాహక ఉపరితలం",
            "B": "సమతుల్య లాటిస్ స్థిరాంకం",
            "C": "అధిక రఫ్‌నెస్",
            "D": "ఉష్ణ విస్తరణ లక్షణాలు",
            "E": "ఎలక్ట్రోస్టాటిక్ సామర్థ్యం"
        }
    },
    "47": {
        "question": "మోనోలేయర్ WSe2లో ఒత్తిడిపై వృద్ధి ఉష్ణోగ్రతను తగ్గించడం ఎలా ప్రభావితం చేస్తుంది?",
        "options": {
            "A": "ఒత్తిడిపై ఎటువంటి ప్రభావం లేదు.",
            "B": "ఒత్తిడిలో క్రమంగా పెరుగుదల.",
            "C": "పదార్థాన్ని ఇన్సులేటర్‌గా మారుస్తుంది.",
            "D": "టెన్సైల్ ఒత్తిడిలో తగ్గింపు.",
            "E": "పదార్థ లక్షణాల పూర్తి నష్టం."
        }
    },
    "48": {
        "question": "ఈ అధ్యయనంలో సూచించినట్లుగా, WSe2 యొక్క PL తీవ్రతను ఒత్తిడి ఎలా ప్రభావితం చేస్తుంది?",
        "options": {
            "A": "పూర్తిగా సున్నాకు తగ్గుతుంది.",
            "B": "PL తీవ్రతను గణనీయంగా పెంచుతుంది.",
            "C": "PL తీవ్రత ప్రభావితం కాదు.",
            "D": "ఒక పరిమితి తర్వాత PL క్వెంచింగ్‌కు కారణమవుతుంది.",
            "E": "PL పీక్‌ను ఇతర ప్రాంతాలకు తరలిస్తుంది."
        }
    },
    "49": {
        "question": "ఏకరీతి ఒత్తిడి పంపిణీని నిర్ధారించడానికి ప్రయోగాత్మక విధానం ఏమిటి?",
        "options": {
            "A": "సూక్ష్మ ఉష్ణ మ్యాపింగ్.",
            "B": "హై-రెసల్యూషన్ రమన్ మ్యాపింగ్.",
            "C": "మాస్ స్పెక్ట్రోమెట్రీ ఇమేజింగ్.",
            "D": "ఎలక్ట్రోమాగ్నెటిక్ ఫీల్డ్ అలైన్‌మెంట్.",
            "E": "ఆప్టికల్ డిఫ్రాక్షన్ అధ్యయనాలు."
        }
    },
    "50": {
        "question": "ఒత్తిడితో ఉన్న మోనోలేయర్ WSe2లో B ఎక్సిటాన్ రెసోనెన్స్‌కు ఏమి జరుగుతుంది?",
        "options": {
            "A": "ఇది పూర్తిగా మాయమవుతుంది.",
            "B": "ఇది మార్పు చెందదు.",
            "C": "ఇది A ఎక్సిటాన్‌తో పోలిస్తే భిన్నంగా మారుతుంది.",
            "D": "ఇది కొత్త పీక్‌గా మారుతుంది.",
            "E": "కొత్త సమ్మతి ఏర్పడుతుంది."
        }
    }
}