{
    "1": {
        "question": "この記事におけるNutriNet-Santé研究の主な目的は何でしたか？",
        "options": {
            "A": "ダイエットサプリメントが減量に与える影響を評価すること。",
            "B": "特定の食事時間と断食が心血管疾患（CVD）リスクに関連するかを調査すること。",
            "C": "ビーガン食が血圧に与える利点を研究すること。",
            "D": "運動強度が心臓の健康に与える影響を評価すること。",
            "E": "睡眠パターンが代謝率に与える影響を探ること。"
        }
    },
    "2": {
        "question": "研究によると、心血管疾患のリスクが高くない行動はどれですか？",
        "options": {
            "A": "午前9時以降に最初の食事を摂ること。",
            "B": "午後9時以降に最後の食事を摂ること。",
            "C": "食事を完全に抜くこと。",
            "D": "特に朝食を抜くこと。",
            "E": "頻繁に間食をすること。"
        }
    },
    "3": {
        "question": "研究コホートに参加した女性の割合は何パーセントですか？",
        "options": {
            "A": "50%",
            "B": "79%",
            "C": "60%",
            "D": "85%",
            "E": "25%"
        }
    },
    "4": {
        "question": "研究参加者の中央値追跡期間はどれくらいでしたか？",
        "options": {
            "A": "3.5年",
            "B": "10.5年",
            "C": "5.0年",
            "D": "7.2年",
            "E": "2.0年"
        }
    },
    "5": {
        "question": "夜間の断食時間と脳血管疾患リスクの関連は何でしたか？",
        "options": {
            "A": "関連は観察されなかった。",
            "B": "断食が長いほどリスクが増加。",
            "C": "1時間ごとに7%リスクが低下。",
            "D": "断食が短いほどリスクが増加。",
            "E": "1時間ごとに50%リスクが低下。"
        }
    },
    "6": {
        "question": "食事時間とCVDリスクの関連が強く見られた人口サブグループはどれですか？",
        "options": {
            "A": "12歳未満の子供",
            "B": "男性",
            "C": "女性",
            "D": "高齢者",
            "E": "ティーンエイジャー"
        }
    },
    "7": {
        "question": "遅い食事時間を持つ参加者の人口統計において観察されなかったパターンはどれですか？",
        "options": {
            "A": "アルコール消費量が多い",
            "B": "教育レベルが高い",
            "C": "就寝時間が遅い",
            "D": "身体活動レベルが高い",
            "E": "年齢が高い"
        }
    },
    "8": {
        "question": "この研究の統計モデルで調整された要因は何ですか？",
        "options": {
            "A": "遺伝的素因",
            "B": "文化的な食事習慣",
            "C": "薬の数",
            "D": "年間世帯収入",
            "E": "クロノタイプ"
        }
    },
    "9": {
        "question": "研究結果によると、食事時間の遅れが心代謝健康に与える影響は何でしたか？",
        "options": {
            "A": "影響の証拠はない。",
            "B": "代謝健康が改善。",
            "C": "体重減少が増加。",
            "D": "心代謝健康に悪影響。",
            "E": "筋肉量が増加。"
        }
    },
    "10": {
        "question": "食事時間に関して研究が探求しなかった側面は何ですか？",
        "options": {
            "A": "心臓の健康への影響",
            "B": "最初の食事の時間",
            "C": "最後の食事の時間",
            "D": "文化的な食事習慣",
            "E": "食事の回数"
        }
    },
    "11": {
        "question": "心血管疾患のリスクを分析するために使用された統計手法はどれですか？",
        "options": {
            "A": "ANOVA",
            "B": "カイ二乗検定",
            "C": "コックス比例ハザードモデル",
            "D": "線形回帰",
            "E": "T検定"
        }
    },
    "12": {
        "question": "NutriNet-Santéコホート研究はどの地域で行われましたか？",
        "options": {
            "A": "アメリカ合衆国",
            "B": "ドイツ",
            "C": "イギリス",
            "D": "フランス",
            "E": "スペイン"
        }
    },
    "13": {
        "question": "研究データによると、最も発生率が高かった心血管イベントはどれですか？",
        "options": {
            "A": "脳卒中",
            "B": "心筋梗塞",
            "C": "狭心症",
            "D": "一過性脳虚血発作",
            "E": "急性冠症候群"
        }
    },
    "14": {
        "question": "参加者における食事時差ボケと関連付けられた行動は何ですか？",
        "options": {
            "A": "一貫した食事時間",
            "B": "頻繁な運動",
            "C": "遅い就寝時間",
            "D": "禁煙",
            "E": "早い就寝時間"
        }
    },
    "15": {
        "question": "記事で議論されている「eTRE」とは何ですか？",
        "options": {
            "A": "早期時間制限食",
            "B": "休息と食事の時間延長",
            "C": "地球外エネルギー",
            "D": "早期全休息食",
            "E": "全体的な食事制限の延長"
        }
    },
    "16": {
        "question": "この研究で食事時間と共に優先された食事の側面は何ですか？",
        "options": {
            "A": "カロリー密度",
            "B": "栄養内容",
            "C": "食事の頻度",
            "D": "食料源",
            "E": "栄養補助食品"
        }
    },
    "17": {
        "question": "研究で交絡因子と見なされなかった要因は何ですか？",
        "options": {
            "A": "喫煙習慣",
            "B": "身体活動",
            "C": "クロノタイプ",
            "D": "遺伝的素因",
            "E": "ベースラインでのBMI"
        }
    },
    "18": {
        "question": "研究の主な制限は何でしたか？",
        "options": {
            "A": "参加者数が不十分",
            "B": "追跡期間が短い",
            "C": "全参加者の睡眠データが不足",
            "D": "地理的制限",
            "E": "ランダム化対照試験の使用"
        }
    },
    "19": {
        "question": "1日の最後の食事を遅らせるとリスクが高くなるグループはどれですか？",
        "options": {
            "A": "男性",
            "B": "女性",
            "C": "子供",
            "D": "高齢者",
            "E": "青年"
        }
    },
    "20": {
        "question": "このコホートで採用された研究デザインのタイプは何ですか？",
        "options": {
            "A": "横断的",
            "B": "ランダム化対照",
            "C": "縦断的",
            "D": "症例対照",
            "E": "実験的"
        }
    },
    "21": {
        "question": "夜間の断食時間はどのように分類されましたか？",
        "options": {
            "A": "0-5時間、5-10時間、10-15時間",
            "B": "6時間、12時間、18時間",
            "C": "10時間以下、10〜12時間、12時間以上",
            "D": "12時間以下、12〜13時間、13時間以上",
            "E": "15時間以下、15〜18時間、18時間以上"
        }
    },
    "22": {
        "question": "食事時間の関連性の焦点ではなかった結果は何ですか？",
        "options": {
            "A": "全体的な心血管疾患",
            "B": "骨密度",
            "C": "冠動脈性心疾患",
            "D": "脳血管疾患",
            "E": "狭心症"
        }
    },
    "23": {
        "question": "食事時間以外で研究が調整したライフスタイル行動は何ですか？",
        "options": {
            "A": "娯楽の選択",
            "B": "宗教活動",
            "C": "アルコール消費",
            "D": "ファッショントレンド",
            "E": "旅行頻度"
        }
    },
    "24": {
        "question": "NutriNet-Santéコホートで採用された食事記録法はどれですか？",
        "options": {
            "A": "隔週のリコール",
            "B": "年間の食事日記",
            "C": "24時間の食事記録",
            "D": "食事頻度質問票",
            "E": "週ごとの食事ログ"
        }
    },
    "25": {
        "question": "クロノニュートリションの分野が調査する領域は何ですか？",
        "options": {
            "A": "微量栄養素の吸収",
            "B": "食事摂取のタイミングと健康",
            "C": "運動プログラムとカロリー消費",
            "D": "消化における生化学的経路",
            "E": "マインドフルイーティングとメンタルヘルス"
        }
    },
    "26": {
        "question": "健康イベントはどのように検証されましたか？",
        "options": {
            "A": "確認なしの自己報告",
            "B": "一般的な調査",
            "C": "医療記録のレビュー",
            "D": "電話インタビュー",
            "E": "オンラインフォーラム"
        }
    },
    "27": {
        "question": "研究によると、心代謝機能に影響を与える生物学的リズムは何ですか？",
        "options": {
            "A": "ウルトラディアンリズム",
            "B": "昼夜リズム",
            "C": "概日リズム",
            "D": "インフラディアンリズム",
            "E": "潮汐リズム"
        }
    },
    "28": {
        "question": "他の研究と一致したモデルの発見はどれですか？",
        "options": {
            "A": "夜間の間食は全体的なCVDリスクを低下させる。",
            "B": "夕食を抜くと血圧が下がる。",
            "C": "遅い食事は代謝マーカーに影響を与えない。",
            "D": "断続的な断食は心代謝健康に有益である。",
            "E": "断続的な断食は全体的な体脂肪率を増加させる。"
        }
    },
    "29": {
        "question": "研究分析に含まれなかった潜在的な交絡因子は何ですか？",
        "options": {
            "A": "所得階層",
            "B": "身体活動",
            "C": "アルコール消費",
            "D": "文化的背景",
            "E": "喫煙習慣"
        }
    },
    "30": {
        "question": "食事時間に関連して分析されなかった参加者の特性は何ですか？",
        "options": {
            "A": "睡眠時間",
            "B": "社会経済的地位",
            "C": "身体活動レベル",
            "D": "娯楽薬物使用",
            "E": "喫煙状況"
        }
    },
    "31": {
        "question": "偽陽性エンドポイントとして使用された疾患状態はどれですか？",
        "options": {
            "A": "2型糖尿病",
            "B": "乳がん",
            "C": "基底細胞癌",
            "D": "高血圧",
            "E": "肥満"
        }
    },
    "32": {
        "question": "インスリン感受性の変動に関連する時間帯はどれですか？",
        "options": {
            "A": "午後遅く",
            "B": "早朝",
            "C": "真夜中",
            "D": "正午",
            "E": "夜遅く"
        }
    },
    "33": {
        "question": "研究で考慮された主要な心血管イベントのカテゴリーはどれですか？",
        "options": {
            "A": "虚血性心不全",
            "B": "末梢動脈疾患",
            "C": "脳血管疾患",
            "D": "僧帽弁逸脱",
            "E": "大動脈解離"
        }
    },
    "34": {
        "question": "この研究で「食事の機会」はどのように定義されましたか？",
        "options": {
            "A": "固形食品の摂取のみ",
            "B": "少なくとも1kcalのカロリー摂取",
            "C": "水のみの飲用",
            "D": "完全な食事を摂ること",
            "E": "温かい飲み物の消費のみ"
        }
    },
    "35": {
        "question": "夜間の断食時間と有意に相互作用しなかった要因はどれですか？",
        "options": {
            "A": "最初の食事の時間",
            "B": "性別",
            "C": "ベースラインでのBMI",
            "D": "閉経状態",
            "E": "クロノタイプ"
        }
    },
    "36": {
        "question": "誤分類バイアスの潜在的な原因を研究はどこに置いていますか？",
        "options": {
            "A": "自己報告された体重記録",
            "B": "食事の定義における文化的変動",
            "C": "季節的な食事の変動",
            "D": "不正確なBMI計算",
            "E": "民族的な食品の分類"
        }
    },
    "37": {
        "question": "研究データは主にどこから得られましたか？",
        "options": {
            "A": "外来診療記録",
            "B": "入院病院報告",
            "C": "自己報告のオンラインアンケート",
            "D": "政府の健康記録",
            "E": "直接的な食事観察"
        }
    },
    "38": {
        "question": "食事記録の正確性を検証するためのアプローチは何でしたか？",
        "options": {
            "A": "未確認の自己報告",
            "B": "バイオマーカーと栄養士インタビューによる検証",
            "C": "食事準備のライブ観察",
            "D": "食料品の購買パターンの分析",
            "E": "食事の写真証拠"
        }
    },
    "39": {
        "question": "食事時間に関連するアルコール消費量の増加の結果は何でしたか？",
        "options": {
            "A": "早い食事時間",
            "B": "食事の回数が増加",
            "C": "遅い食事時間",
            "D": "食事頻度が減少",
            "E": "食事時間に影響なし"
        }
    },
    "40": {
        "question": "CVDイベントの分類システムとして使用されたのはどれですか？",
        "options": {
            "A": "DSM-V",
            "B": "ICD-CM",
            "C": "SNOMED CT",
            "D": "RXNorm",
            "E": "MedDRA"
        }
    },
    "41": {
        "question": "研究で交絡の問題はどのように対処されましたか？",
        "options": {
            "A": "ランダムな地理的割り当て",
            "B": "プラセボ対照群",
            "C": "多変量コックス比例ハザードモデル",
            "D": "ボランティアの自己選択",
            "E": "クロスオーバー実験デザイン"
        }
    },
    "42": {
        "question": "以前の実験研究と一致したと考えられた発見はどれですか？",
        "options": {
            "A": "朝にエネルギーを集中させると体重が減少した。",
            "B": "遅い食事時間が代謝に利益をもたらした。",
            "C": "朝食を抜くと心血管の健康が改善した。",
            "D": "時間制限食が心代謝マーカーを改善した。",
            "E": "カロリー摂取量の増加は体重に影響を与えない。"
        }
    },
    "43": {
        "question": "食事の回数と有意な関連を示さなかった主要な結果はどれですか？",
        "options": {
            "A": "全体的な心血管疾患リスク",
            "B": "冠動脈性心疾患リスク",
            "C": "体格指数",
            "D": "血圧",
            "E": "アルコール消費"
        }
    },
    "44": {
        "question": "この研究のユニークな方法論的アプローチは何でしたか？",
        "options": {
            "A": "半年ごとの24時間食事記録",
            "B": "手書きの食事日記",
            "C": "食事評価なし",
            "D": "ラボでの食事テスト",
            "E": "ビデオで記録された食事時間"
        }
    },
    "45": {
        "question": "平日と週末の食事時間の違いを指す概念は何ですか？",
        "options": {
            "A": "食事の同期",
            "B": "食事の時計の変動",
            "C": "カロリーの変動",
            "D": "食事の時差ボケ",
            "E": "食事の不一致"
        }
    },
    "46": {
        "question": "食事時間に関連して観察された結果がなかった要因はどれですか？",
        "options": {
            "A": "最初の食事の時間",
            "B": "最後の食事の時間",
            "C": "食事の回数",
            "D": "アルコール摂取のタイミング",
            "E": "食事の質"
        }
    },
    "47": {
        "question": "研究によると、食事時間が心代謝健康に影響を与える可能性があるのは、1日のどの期間と一致する場合ですか？",
        "options": {
            "A": "休息期",
            "B": "活動期",
            "C": "レム睡眠",
            "D": "夜間",
            "E": "朝の時間"
        }
    },
    "48": {
        "question": "食事時間との相互作用を探求しなかった人口統計要因はどれですか？",
        "options": {
            "A": "世帯収入",
            "B": "性別",
            "C": "年齢",
            "D": "閉経状態",
            "E": "民族性"
        }
    },
    "49": {
        "question": "研究はどのようにして身体活動を評価しましたか？",
        "options": {
            "A": "歩数計",
            "B": "対面フィットネステスト",
            "C": "国際身体活動質問票",
            "D": "週ごとのジム出席",
            "E": "フィットネスアプリの使用"
        }
    },
    "50": {
        "question": "研究で行われた主な感度分析は何でしたか？",
        "options": {
            "A": "身長の変動を調整",
            "B": "男性参加者のみを含む",
            "C": "ベースラインの慢性疾患を考慮",
            "D": "すべてのアルコール消費者を除外",
            "E": "座りがちな個人のみをテスト"
        }
    }
}