{
    "1": {
        "question": "Dans la Fig. 1c, quelle est l'efficacité de pointe simulée du coupleur vertical conçu à l'envers ?",
        "options": {
            "A": "10%",
            "B": "15%",
            "C": "25%",
            "D": "30%",
            "E": "35%"
        }
    },
    "2": {
        "question": "Comme montré dans la Fig. 2e, quelle est l'efficacité de pointe du coupleur lors de l'utilisation de fibres multimodes (MMF) ?",
        "options": {
            "A": "15%",
            "B": "20%",
            "C": "21%",
            "D": "26,5%",
            "E": "30%"
        }
    },
    "3": {
        "question": "Dans la Fig. 3c, de combien le taux de comptage est-il supérieur avec un coupleur à réseau par rapport au dispositif à encoche ?",
        "options": {
            "A": "10 fois",
            "B": "50 fois",
            "C": "100 fois",
            "D": "550 fois",
            "E": "625 fois"
        }
    },
    "4": {
        "question": "Quelle est l'efficacité simulée du séparateur de guide d'ondes montré dans la Fig. 4a ?",
        "options": {
            "A": "75%",
            "B": "85%",
            "C": "90%",
            "D": "95%",
            "E": "100%"
        }
    },
    "5": {
        "question": "Selon la Fig. 5f, quel design montre la plus haute efficacité pour les coupleurs verticaux ?",
        "options": {
            "A": "a",
            "B": "b",
            "C": "c",
            "D": "d",
            "E": "e"
        }
    },
    "6": {
        "question": "Dans la Fig. 1f, quel type de structure est montré après optimisation ?",
        "options": {
            "A": "Continue",
            "B": "Discrète",
            "C": "Hybride",
            "D": "Linéaire",
            "E": "Courbée"
        }
    },
    "7": {
        "question": "Selon la Fig. 2d, comment la polarisation affecte-t-elle l'efficacité de couplage ?",
        "options": {
            "A": "Aucun effet",
            "B": "Augmente de 10x",
            "C": "Réduit de 5x",
            "D": "Augmente de 5x",
            "E": "Réduit de 10x"
        }
    },
    "8": {
        "question": "Dans la Fig. 3a, quel type d'interface est associé à la cavité à cristal photonique à nanofaisceau ?",
        "options": {
            "A": "Coupleur à réseau",
            "B": "Encoche",
            "C": "Lentille",
            "D": "Diviseur de faisceau",
            "E": "Réflecteur"
        }
    },
    "9": {
        "question": "Quelle est l'efficacité du coupleur symétrique vertical suspendu dans l'air montré dans la Fig. 5a ?",
        "options": {
            "A": "44,7%",
            "B": "51,0%",
            "C": "67,9%",
            "D": "72,4%",
            "E": "86,6%"
        }
    },
    "10": {
        "question": "Selon la Fig. 2f, que représente la zone ombrée en rouge ?",
        "options": {
            "A": "Valeur moyenne",
            "B": "Valeur de pointe",
            "C": "Valeur minimale",
            "D": "Écart type",
            "E": "Valeur maximale"
        }
    },
    "11": {
        "question": "Quelle efficacité est atteinte pour les coupleurs sur SiO2 avec des réflecteurs arrière en aluminium selon la Fig. 5d ?",
        "options": {
            "A": "44,7%",
            "B": "51,0%",
            "C": "67,9%",
            "D": "72,4%",
            "E": "86,6%"
        }
    },
    "12": {
        "question": "La Fig. 4c montre que les cavités peuvent être accordées en résonance via quelle méthode ?",
        "options": {
            "A": "Changement de température",
            "B": "Champ magnétique",
            "C": "Condensation de gaz",
            "D": "Courant électrique",
            "E": "Changement de pression"
        }
    },
    "13": {
        "question": "Dans la Fig. 2a, quelles structures connectent les coupleurs verticaux ?",
        "options": {
            "A": "Encoches",
            "B": "Guides d'ondes",
            "C": "Microlentilles",
            "D": "Résonateurs",
            "E": "Miroirs"
        }
    },
    "14": {
        "question": "En se référant à la Fig. 3d, quelle couleur de ligne représente le couplage à travers le coupleur vertical ?",
        "options": {
            "A": "Rouge",
            "B": "Vert",
            "C": "Bleu",
            "D": "Noir",
            "E": "Jaune"
        }
    },
    "15": {
        "question": "Dans la Fig. 1e, à combien d'itérations l'efficacité commence-t-elle à diminuer légèrement ?",
        "options": {
            "A": "100",
            "B": "200",
            "C": "300",
            "D": "400",
            "E": "500"
        }
    },
    "16": {
        "question": "Quelle efficacité est atteinte pour les structures suspendues dans l'air avec des réflecteurs arrière en aluminium selon la Fig. 5e ?",
        "options": {
            "A": "44,7%",
            "B": "51,0%",
            "C": "67,9%",
            "D": "72,4%",
            "E": "86,6%"
        }
    },
    "17": {
        "question": "Selon la Fig. 2b, quel angle est associé à la découpe du coupleur vertical ?",
        "options": {
            "A": "70°",
            "B": "75°",
            "C": "80°",
            "D": "85°",
            "E": "90°"
        }
    },
    "18": {
        "question": "Dans la Fig. 5b, quel substrat est utilisé pour le coupleur vertical ?",
        "options": {
            "A": "Air",
            "B": "Verre",
            "C": "Silicium",
            "D": "Aluminium",
            "E": "SiO2"
        }
    },
    "19": {
        "question": "Que indiquent les flèches bleues dans la Fig. 3c ?",
        "options": {
            "A": "Points de dommage",
            "B": "Efficacités de pointe",
            "C": "Résonances de cavité",
            "D": "Erreurs de mesure",
            "E": "Points de référence"
        }
    },
    "20": {
        "question": "Quel design dans la Fig. 5 montre la plus grande amélioration d'efficacité en utilisant des réflecteurs arrière ?",
        "options": {
            "A": "a",
            "B": "b",
            "C": "c",
            "D": "d",
            "E": "e"
        }
    }
}